{
  "id": "55e9c1fb-84f8-4abc-9b0e-19f4802552f3",
  "prevId": "00000000-0000-0000-0000-000000000000",
  "version": "7",
  "dialect": "postgresql",
  "tables": {
    "public.grocery_list_items": {
      "name": "grocery_list_items",
      "schema": "",
      "columns": {
        "id": {
          "name": "id",
          "type": "uuid",
          "primaryKey": true,
          "notNull": true,
          "default": "gen_random_uuid()"
        },
        "grocery_list_id": {
          "name": "grocery_list_id",
          "type": "uuid",
          "primaryKey": false,
          "notNull": true
        },
        "name": {
          "name": "name",
          "type": "text",
          "primaryKey": false,
          "notNull": true
        },
        "quantity": {
          "name": "quantity",
          "type": "text",
          "primaryKey": false,
          "notNull": false
        },
        "unit": {
          "name": "unit",
          "type": "text",
          "primaryKey": false,
          "notNull": false
        },
        "category": {
          "name": "category",
          "type": "text",
          "primaryKey": false,
          "notNull": false
        },
        "is_checked": {
          "name": "is_checked",
          "type": "boolean",
          "primaryKey": false,
          "notNull": true,
          "default": false
        },
        "pantry_match": {
          "name": "pantry_match",
          "type": "boolean",
          "primaryKey": false,
          "notNull": true,
          "default": false
        },
        "source_recipe_ids": {
          "name": "source_recipe_ids",
          "type": "jsonb",
          "primaryKey": false,
          "notNull": true,
          "default": "'[]'::jsonb"
        },
        "created_at": {
          "name": "created_at",
          "type": "timestamp with time zone",
          "primaryKey": false,
          "notNull": true,
          "default": "now()"
        }
      },
      "indexes": {
        "grocery_list_items_grocery_list_id_idx": {
          "name": "grocery_list_items_grocery_list_id_idx",
          "columns": [
            {
              "expression": "grocery_list_id",
              "isExpression": false,
              "asc": true,
              "nulls": "last"
            }
          ],
          "isUnique": false,
          "concurrently": false,
          "method": "btree",
          "with": {}
        }
      },
      "foreignKeys": {
        "grocery_list_items_grocery_list_id_grocery_lists_id_fk": {
          "name": "grocery_list_items_grocery_list_id_grocery_lists_id_fk",
          "tableFrom": "grocery_list_items",
          "tableTo": "grocery_lists",
          "columnsFrom": [
            "grocery_list_id"
          ],
          "columnsTo": [
            "id"
          ],
          "onDelete": "cascade",
          "onUpdate": "no action"
        }
      },
      "compositePrimaryKeys": {},
      "uniqueConstraints": {},
      "policies": {
        "grocery_list_items_select_own_list": {
          "name": "grocery_list_items_select_own_list",
          "as": "PERMISSIVE",
          "for": "SELECT",
          "to": [
            "authenticated"
          ],
          "using": "(select auth.uid()) is not null and exists (select 1 from \"grocery_lists\" where \"grocery_lists\".\"id\" = \"grocery_list_items\".\"grocery_list_id\" and \"grocery_lists\".\"user_id\" = (select auth.uid()))"
        },
        "grocery_list_items_insert_own_list": {
          "name": "grocery_list_items_insert_own_list",
          "as": "PERMISSIVE",
          "for": "INSERT",
          "to": [
            "authenticated"
          ],
          "withCheck": "(select auth.uid()) is not null and exists (select 1 from \"grocery_lists\" where \"grocery_lists\".\"id\" = \"grocery_list_items\".\"grocery_list_id\" and \"grocery_lists\".\"user_id\" = (select auth.uid()))"
        },
        "grocery_list_items_update_own_list": {
          "name": "grocery_list_items_update_own_list",
          "as": "PERMISSIVE",
          "for": "UPDATE",
          "to": [
            "authenticated"
          ],
          "using": "(select auth.uid()) is not null and exists (select 1 from \"grocery_lists\" where \"grocery_lists\".\"id\" = \"grocery_list_items\".\"grocery_list_id\" and \"grocery_lists\".\"user_id\" = (select auth.uid()))",
          "withCheck": "(select auth.uid()) is not null and exists (select 1 from \"grocery_lists\" where \"grocery_lists\".\"id\" = \"grocery_list_items\".\"grocery_list_id\" and \"grocery_lists\".\"user_id\" = (select auth.uid()))"
        },
        "grocery_list_items_delete_own_list": {
          "name": "grocery_list_items_delete_own_list",
          "as": "PERMISSIVE",
          "for": "DELETE",
          "to": [
            "authenticated"
          ],
          "using": "(select auth.uid()) is not null and exists (select 1 from \"grocery_lists\" where \"grocery_lists\".\"id\" = \"grocery_list_items\".\"grocery_list_id\" and \"grocery_lists\".\"user_id\" = (select auth.uid()))"
        }
      },
      "checkConstraints": {},
      "isRLSEnabled": true
    },
    "public.grocery_lists": {
      "name": "grocery_lists",
      "schema": "",
      "columns": {
        "id": {
          "name": "id",
          "type": "uuid",
          "primaryKey": true,
          "notNull": true,
          "default": "gen_random_uuid()"
        },
        "user_id": {
          "name": "user_id",
          "type": "uuid",
          "primaryKey": false,
          "notNull": true
        },
        "title": {
          "name": "title",
          "type": "text",
          "primaryKey": false,
          "notNull": true
        },
        "created_at": {
          "name": "created_at",
          "type": "timestamp with time zone",
          "primaryKey": false,
          "notNull": true,
          "default": "now()"
        },
        "updated_at": {
          "name": "updated_at",
          "type": "timestamp with time zone",
          "primaryKey": false,
          "notNull": true,
          "default": "now()"
        }
      },
      "indexes": {
        "grocery_lists_user_id_idx": {
          "name": "grocery_lists_user_id_idx",
          "columns": [
            {
              "expression": "user_id",
              "isExpression": false,
              "asc": true,
              "nulls": "last"
            }
          ],
          "isUnique": false,
          "concurrently": false,
          "method": "btree",
          "with": {}
        }
      },
      "foreignKeys": {
        "grocery_lists_user_id_users_id_fk": {
          "name": "grocery_lists_user_id_users_id_fk",
          "tableFrom": "grocery_lists",
          "tableTo": "users",
          "schemaTo": "auth",
          "columnsFrom": [
            "user_id"
          ],
          "columnsTo": [
            "id"
          ],
          "onDelete": "cascade",
          "onUpdate": "no action"
        }
      },
      "compositePrimaryKeys": {},
      "uniqueConstraints": {},
      "policies": {
        "grocery_lists_select_own": {
          "name": "grocery_lists_select_own",
          "as": "PERMISSIVE",
          "for": "SELECT",
          "to": [
            "authenticated"
          ],
          "using": "(select auth.uid()) is not null and (select auth.uid()) = \"grocery_lists\".\"user_id\""
        },
        "grocery_lists_insert_own": {
          "name": "grocery_lists_insert_own",
          "as": "PERMISSIVE",
          "for": "INSERT",
          "to": [
            "authenticated"
          ],
          "withCheck": "(select auth.uid()) is not null and (select auth.uid()) = \"grocery_lists\".\"user_id\""
        },
        "grocery_lists_update_own": {
          "name": "grocery_lists_update_own",
          "as": "PERMISSIVE",
          "for": "UPDATE",
          "to": [
            "authenticated"
          ],
          "using": "(select auth.uid()) is not null and (select auth.uid()) = \"grocery_lists\".\"user_id\"",
          "withCheck": "(select auth.uid()) is not null and (select auth.uid()) = \"grocery_lists\".\"user_id\""
        },
        "grocery_lists_delete_own": {
          "name": "grocery_lists_delete_own",
          "as": "PERMISSIVE",
          "for": "DELETE",
          "to": [
            "authenticated"
          ],
          "using": "(select auth.uid()) is not null and (select auth.uid()) = \"grocery_lists\".\"user_id\""
        }
      },
      "checkConstraints": {},
      "isRLSEnabled": true
    },
    "public.pantry_items": {
      "name": "pantry_items",
      "schema": "",
      "columns": {
        "id": {
          "name": "id",
          "type": "uuid",
          "primaryKey": true,
          "notNull": true,
          "default": "gen_random_uuid()"
        },
        "user_id": {
          "name": "user_id",
          "type": "uuid",
          "primaryKey": false,
          "notNull": true
        },
        "name": {
          "name": "name",
          "type": "text",
          "primaryKey": false,
          "notNull": true
        },
        "quantity": {
          "name": "quantity",
          "type": "text",
          "primaryKey": false,
          "notNull": false
        },
        "unit": {
          "name": "unit",
          "type": "text",
          "primaryKey": false,
          "notNull": false
        },
        "category": {
          "name": "category",
          "type": "text",
          "primaryKey": false,
          "notNull": false
        },
        "notes": {
          "name": "notes",
          "type": "text",
          "primaryKey": false,
          "notNull": false
        },
        "created_at": {
          "name": "created_at",
          "type": "timestamp with time zone",
          "primaryKey": false,
          "notNull": true,
          "default": "now()"
        },
        "updated_at": {
          "name": "updated_at",
          "type": "timestamp with time zone",
          "primaryKey": false,
          "notNull": true,
          "default": "now()"
        }
      },
      "indexes": {
        "pantry_items_user_id_idx": {
          "name": "pantry_items_user_id_idx",
          "columns": [
            {
              "expression": "user_id",
              "isExpression": false,
              "asc": true,
              "nulls": "last"
            }
          ],
          "isUnique": false,
          "concurrently": false,
          "method": "btree",
          "with": {}
        }
      },
      "foreignKeys": {
        "pantry_items_user_id_users_id_fk": {
          "name": "pantry_items_user_id_users_id_fk",
          "tableFrom": "pantry_items",
          "tableTo": "users",
          "schemaTo": "auth",
          "columnsFrom": [
            "user_id"
          ],
          "columnsTo": [
            "id"
          ],
          "onDelete": "cascade",
          "onUpdate": "no action"
        }
      },
      "compositePrimaryKeys": {},
      "uniqueConstraints": {},
      "policies": {
        "pantry_items_select_own": {
          "name": "pantry_items_select_own",
          "as": "PERMISSIVE",
          "for": "SELECT",
          "to": [
            "authenticated"
          ],
          "using": "(select auth.uid()) is not null and (select auth.uid()) = \"pantry_items\".\"user_id\""
        },
        "pantry_items_insert_own": {
          "name": "pantry_items_insert_own",
          "as": "PERMISSIVE",
          "for": "INSERT",
          "to": [
            "authenticated"
          ],
          "withCheck": "(select auth.uid()) is not null and (select auth.uid()) = \"pantry_items\".\"user_id\""
        },
        "pantry_items_update_own": {
          "name": "pantry_items_update_own",
          "as": "PERMISSIVE",
          "for": "UPDATE",
          "to": [
            "authenticated"
          ],
          "using": "(select auth.uid()) is not null and (select auth.uid()) = \"pantry_items\".\"user_id\"",
          "withCheck": "(select auth.uid()) is not null and (select auth.uid()) = \"pantry_items\".\"user_id\""
        },
        "pantry_items_delete_own": {
          "name": "pantry_items_delete_own",
          "as": "PERMISSIVE",
          "for": "DELETE",
          "to": [
            "authenticated"
          ],
          "using": "(select auth.uid()) is not null and (select auth.uid()) = \"pantry_items\".\"user_id\""
        }
      },
      "checkConstraints": {},
      "isRLSEnabled": true
    },
    "public.recipe_ingredients": {
      "name": "recipe_ingredients",
      "schema": "",
      "columns": {
        "id": {
          "name": "id",
          "type": "uuid",
          "primaryKey": true,
          "notNull": true,
          "default": "gen_random_uuid()"
        },
        "recipe_id": {
          "name": "recipe_id",
          "type": "uuid",
          "primaryKey": false,
          "notNull": true
        },
        "name": {
          "name": "name",
          "type": "text",
          "primaryKey": false,
          "notNull": true
        },
        "raw_text": {
          "name": "raw_text",
          "type": "text",
          "primaryKey": false,
          "notNull": false
        },
        "quantity": {
          "name": "quantity",
          "type": "text",
          "primaryKey": false,
          "notNull": false
        },
        "unit": {
          "name": "unit",
          "type": "text",
          "primaryKey": false,
          "notNull": false
        },
        "category": {
          "name": "category",
          "type": "text",
          "primaryKey": false,
          "notNull": false
        },
        "sort_order": {
          "name": "sort_order",
          "type": "integer",
          "primaryKey": false,
          "notNull": true,
          "default": 0
        }
      },
      "indexes": {
        "recipe_ingredients_recipe_id_idx": {
          "name": "recipe_ingredients_recipe_id_idx",
          "columns": [
            {
              "expression": "recipe_id",
              "isExpression": false,
              "asc": true,
              "nulls": "last"
            }
          ],
          "isUnique": false,
          "concurrently": false,
          "method": "btree",
          "with": {}
        }
      },
      "foreignKeys": {
        "recipe_ingredients_recipe_id_recipes_id_fk": {
          "name": "recipe_ingredients_recipe_id_recipes_id_fk",
          "tableFrom": "recipe_ingredients",
          "tableTo": "recipes",
          "columnsFrom": [
            "recipe_id"
          ],
          "columnsTo": [
            "id"
          ],
          "onDelete": "cascade",
          "onUpdate": "no action"
        }
      },
      "compositePrimaryKeys": {},
      "uniqueConstraints": {},
      "policies": {
        "recipe_ingredients_select_own_recipe": {
          "name": "recipe_ingredients_select_own_recipe",
          "as": "PERMISSIVE",
          "for": "SELECT",
          "to": [
            "authenticated"
          ],
          "using": "(select auth.uid()) is not null and exists (select 1 from \"recipes\" where \"recipes\".\"id\" = \"recipe_ingredients\".\"recipe_id\" and \"recipes\".\"user_id\" = (select auth.uid()))"
        },
        "recipe_ingredients_insert_own_recipe": {
          "name": "recipe_ingredients_insert_own_recipe",
          "as": "PERMISSIVE",
          "for": "INSERT",
          "to": [
            "authenticated"
          ],
          "withCheck": "(select auth.uid()) is not null and exists (select 1 from \"recipes\" where \"recipes\".\"id\" = \"recipe_ingredients\".\"recipe_id\" and \"recipes\".\"user_id\" = (select auth.uid()))"
        },
        "recipe_ingredients_update_own_recipe": {
          "name": "recipe_ingredients_update_own_recipe",
          "as": "PERMISSIVE",
          "for": "UPDATE",
          "to": [
            "authenticated"
          ],
          "using": "(select auth.uid()) is not null and exists (select 1 from \"recipes\" where \"recipes\".\"id\" = \"recipe_ingredients\".\"recipe_id\" and \"recipes\".\"user_id\" = (select auth.uid()))",
          "withCheck": "(select auth.uid()) is not null and exists (select 1 from \"recipes\" where \"recipes\".\"id\" = \"recipe_ingredients\".\"recipe_id\" and \"recipes\".\"user_id\" = (select auth.uid()))"
        },
        "recipe_ingredients_delete_own_recipe": {
          "name": "recipe_ingredients_delete_own_recipe",
          "as": "PERMISSIVE",
          "for": "DELETE",
          "to": [
            "authenticated"
          ],
          "using": "(select auth.uid()) is not null and exists (select 1 from \"recipes\" where \"recipes\".\"id\" = \"recipe_ingredients\".\"recipe_id\" and \"recipes\".\"user_id\" = (select auth.uid()))"
        }
      },
      "checkConstraints": {},
      "isRLSEnabled": true
    },
    "public.recipe_steps": {
      "name": "recipe_steps",
      "schema": "",
      "columns": {
        "id": {
          "name": "id",
          "type": "uuid",
          "primaryKey": true,
          "notNull": true,
          "default": "gen_random_uuid()"
        },
        "recipe_id": {
          "name": "recipe_id",
          "type": "uuid",
          "primaryKey": false,
          "notNull": true
        },
        "step_number": {
          "name": "step_number",
          "type": "integer",
          "primaryKey": false,
          "notNull": true
        },
        "instruction": {
          "name": "instruction",
          "type": "text",
          "primaryKey": false,
          "notNull": true
        }
      },
      "indexes": {
        "recipe_steps_recipe_id_idx": {
          "name": "recipe_steps_recipe_id_idx",
          "columns": [
            {
              "expression": "recipe_id",
              "isExpression": false,
              "asc": true,
              "nulls": "last"
            }
          ],
          "isUnique": false,
          "concurrently": false,
          "method": "btree",
          "with": {}
        }
      },
      "foreignKeys": {
        "recipe_steps_recipe_id_recipes_id_fk": {
          "name": "recipe_steps_recipe_id_recipes_id_fk",
          "tableFrom": "recipe_steps",
          "tableTo": "recipes",
          "columnsFrom": [
            "recipe_id"
          ],
          "columnsTo": [
            "id"
          ],
          "onDelete": "cascade",
          "onUpdate": "no action"
        }
      },
      "compositePrimaryKeys": {},
      "uniqueConstraints": {},
      "policies": {
        "recipe_steps_select_own_recipe": {
          "name": "recipe_steps_select_own_recipe",
          "as": "PERMISSIVE",
          "for": "SELECT",
          "to": [
            "authenticated"
          ],
          "using": "(select auth.uid()) is not null and exists (select 1 from \"recipes\" where \"recipes\".\"id\" = \"recipe_steps\".\"recipe_id\" and \"recipes\".\"user_id\" = (select auth.uid()))"
        },
        "recipe_steps_insert_own_recipe": {
          "name": "recipe_steps_insert_own_recipe",
          "as": "PERMISSIVE",
          "for": "INSERT",
          "to": [
            "authenticated"
          ],
          "withCheck": "(select auth.uid()) is not null and exists (select 1 from \"recipes\" where \"recipes\".\"id\" = \"recipe_steps\".\"recipe_id\" and \"recipes\".\"user_id\" = (select auth.uid()))"
        },
        "recipe_steps_update_own_recipe": {
          "name": "recipe_steps_update_own_recipe",
          "as": "PERMISSIVE",
          "for": "UPDATE",
          "to": [
            "authenticated"
          ],
          "using": "(select auth.uid()) is not null and exists (select 1 from \"recipes\" where \"recipes\".\"id\" = \"recipe_steps\".\"recipe_id\" and \"recipes\".\"user_id\" = (select auth.uid()))",
          "withCheck": "(select auth.uid()) is not null and exists (select 1 from \"recipes\" where \"recipes\".\"id\" = \"recipe_steps\".\"recipe_id\" and \"recipes\".\"user_id\" = (select auth.uid()))"
        },
        "recipe_steps_delete_own_recipe": {
          "name": "recipe_steps_delete_own_recipe",
          "as": "PERMISSIVE",
          "for": "DELETE",
          "to": [
            "authenticated"
          ],
          "using": "(select auth.uid()) is not null and exists (select 1 from \"recipes\" where \"recipes\".\"id\" = \"recipe_steps\".\"recipe_id\" and \"recipes\".\"user_id\" = (select auth.uid()))"
        }
      },
      "checkConstraints": {},
      "isRLSEnabled": true
    },
    "public.recipe_tag_assignments": {
      "name": "recipe_tag_assignments",
      "schema": "",
      "columns": {
        "recipe_id": {
          "name": "recipe_id",
          "type": "uuid",
          "primaryKey": false,
          "notNull": true
        },
        "tag_id": {
          "name": "tag_id",
          "type": "uuid",
          "primaryKey": false,
          "notNull": true
        }
      },
      "indexes": {
        "recipe_tag_assignments_recipe_id_idx": {
          "name": "recipe_tag_assignments_recipe_id_idx",
          "columns": [
            {
              "expression": "recipe_id",
              "isExpression": false,
              "asc": true,
              "nulls": "last"
            }
          ],
          "isUnique": false,
          "concurrently": false,
          "method": "btree",
          "with": {}
        },
        "recipe_tag_assignments_tag_id_idx": {
          "name": "recipe_tag_assignments_tag_id_idx",
          "columns": [
            {
              "expression": "tag_id",
              "isExpression": false,
              "asc": true,
              "nulls": "last"
            }
          ],
          "isUnique": false,
          "concurrently": false,
          "method": "btree",
          "with": {}
        }
      },
      "foreignKeys": {
        "recipe_tag_assignments_recipe_id_recipes_id_fk": {
          "name": "recipe_tag_assignments_recipe_id_recipes_id_fk",
          "tableFrom": "recipe_tag_assignments",
          "tableTo": "recipes",
          "columnsFrom": [
            "recipe_id"
          ],
          "columnsTo": [
            "id"
          ],
          "onDelete": "cascade",
          "onUpdate": "no action"
        },
        "recipe_tag_assignments_tag_id_recipe_tags_id_fk": {
          "name": "recipe_tag_assignments_tag_id_recipe_tags_id_fk",
          "tableFrom": "recipe_tag_assignments",
          "tableTo": "recipe_tags",
          "columnsFrom": [
            "tag_id"
          ],
          "columnsTo": [
            "id"
          ],
          "onDelete": "cascade",
          "onUpdate": "no action"
        }
      },
      "compositePrimaryKeys": {
        "recipe_tag_assignments_recipe_id_tag_id_pk": {
          "name": "recipe_tag_assignments_recipe_id_tag_id_pk",
          "columns": [
            "recipe_id",
            "tag_id"
          ]
        }
      },
      "uniqueConstraints": {},
      "policies": {
        "recipe_tag_assignments_select_own": {
          "name": "recipe_tag_assignments_select_own",
          "as": "PERMISSIVE",
          "for": "SELECT",
          "to": [
            "authenticated"
          ],
          "using": "(select auth.uid()) is not null and exists (select 1 from \"recipes\" where \"recipes\".\"id\" = \"recipe_tag_assignments\".\"recipe_id\" and \"recipes\".\"user_id\" = (select auth.uid())) and exists (select 1 from \"recipe_tags\" where \"recipe_tags\".\"id\" = \"recipe_tag_assignments\".\"tag_id\" and \"recipe_tags\".\"user_id\" = (select auth.uid()))"
        },
        "recipe_tag_assignments_insert_own": {
          "name": "recipe_tag_assignments_insert_own",
          "as": "PERMISSIVE",
          "for": "INSERT",
          "to": [
            "authenticated"
          ],
          "withCheck": "(select auth.uid()) is not null and exists (select 1 from \"recipes\" where \"recipes\".\"id\" = \"recipe_tag_assignments\".\"recipe_id\" and \"recipes\".\"user_id\" = (select auth.uid())) and exists (select 1 from \"recipe_tags\" where \"recipe_tags\".\"id\" = \"recipe_tag_assignments\".\"tag_id\" and \"recipe_tags\".\"user_id\" = (select auth.uid()))"
        },
        "recipe_tag_assignments_delete_own": {
          "name": "recipe_tag_assignments_delete_own",
          "as": "PERMISSIVE",
          "for": "DELETE",
          "to": [
            "authenticated"
          ],
          "using": "(select auth.uid()) is not null and exists (select 1 from \"recipes\" where \"recipes\".\"id\" = \"recipe_tag_assignments\".\"recipe_id\" and \"recipes\".\"user_id\" = (select auth.uid())) and exists (select 1 from \"recipe_tags\" where \"recipe_tags\".\"id\" = \"recipe_tag_assignments\".\"tag_id\" and \"recipe_tags\".\"user_id\" = (select auth.uid()))"
        }
      },
      "checkConstraints": {},
      "isRLSEnabled": true
    },
    "public.recipe_tags": {
      "name": "recipe_tags",
      "schema": "",
      "columns": {
        "id": {
          "name": "id",
          "type": "uuid",
          "primaryKey": true,
          "notNull": true,
          "default": "gen_random_uuid()"
        },
        "user_id": {
          "name": "user_id",
          "type": "uuid",
          "primaryKey": false,
          "notNull": true
        },
        "name": {
          "name": "name",
          "type": "text",
          "primaryKey": false,
          "notNull": true
        },
        "created_at": {
          "name": "created_at",
          "type": "timestamp with time zone",
          "primaryKey": false,
          "notNull": true,
          "default": "now()"
        }
      },
      "indexes": {
        "recipe_tags_user_id_idx": {
          "name": "recipe_tags_user_id_idx",
          "columns": [
            {
              "expression": "user_id",
              "isExpression": false,
              "asc": true,
              "nulls": "last"
            }
          ],
          "isUnique": false,
          "concurrently": false,
          "method": "btree",
          "with": {}
        },
        "recipe_tags_user_id_name_idx": {
          "name": "recipe_tags_user_id_name_idx",
          "columns": [
            {
              "expression": "user_id",
              "isExpression": false,
              "asc": true,
              "nulls": "last"
            },
            {
              "expression": "name",
              "isExpression": false,
              "asc": true,
              "nulls": "last"
            }
          ],
          "isUnique": true,
          "concurrently": false,
          "method": "btree",
          "with": {}
        }
      },
      "foreignKeys": {
        "recipe_tags_user_id_users_id_fk": {
          "name": "recipe_tags_user_id_users_id_fk",
          "tableFrom": "recipe_tags",
          "tableTo": "users",
          "schemaTo": "auth",
          "columnsFrom": [
            "user_id"
          ],
          "columnsTo": [
            "id"
          ],
          "onDelete": "cascade",
          "onUpdate": "no action"
        }
      },
      "compositePrimaryKeys": {},
      "uniqueConstraints": {},
      "policies": {
        "recipe_tags_select_own": {
          "name": "recipe_tags_select_own",
          "as": "PERMISSIVE",
          "for": "SELECT",
          "to": [
            "authenticated"
          ],
          "using": "(select auth.uid()) is not null and (select auth.uid()) = \"recipe_tags\".\"user_id\""
        },
        "recipe_tags_insert_own": {
          "name": "recipe_tags_insert_own",
          "as": "PERMISSIVE",
          "for": "INSERT",
          "to": [
            "authenticated"
          ],
          "withCheck": "(select auth.uid()) is not null and (select auth.uid()) = \"recipe_tags\".\"user_id\""
        },
        "recipe_tags_update_own": {
          "name": "recipe_tags_update_own",
          "as": "PERMISSIVE",
          "for": "UPDATE",
          "to": [
            "authenticated"
          ],
          "using": "(select auth.uid()) is not null and (select auth.uid()) = \"recipe_tags\".\"user_id\"",
          "withCheck": "(select auth.uid()) is not null and (select auth.uid()) = \"recipe_tags\".\"user_id\""
        },
        "recipe_tags_delete_own": {
          "name": "recipe_tags_delete_own",
          "as": "PERMISSIVE",
          "for": "DELETE",
          "to": [
            "authenticated"
          ],
          "using": "(select auth.uid()) is not null and (select auth.uid()) = \"recipe_tags\".\"user_id\""
        }
      },
      "checkConstraints": {},
      "isRLSEnabled": true
    },
    "public.recipes": {
      "name": "recipes",
      "schema": "",
      "columns": {
        "id": {
          "name": "id",
          "type": "uuid",
          "primaryKey": true,
          "notNull": true,
          "default": "gen_random_uuid()"
        },
        "user_id": {
          "name": "user_id",
          "type": "uuid",
          "primaryKey": false,
          "notNull": true
        },
        "title": {
          "name": "title",
          "type": "text",
          "primaryKey": false,
          "notNull": true
        },
        "description": {
          "name": "description",
          "type": "text",
          "primaryKey": false,
          "notNull": false
        },
        "image_url": {
          "name": "image_url",
          "type": "text",
          "primaryKey": false,
          "notNull": false
        },
        "prep_time": {
          "name": "prep_time",
          "type": "integer",
          "primaryKey": false,
          "notNull": false
        },
        "cook_time": {
          "name": "cook_time",
          "type": "integer",
          "primaryKey": false,
          "notNull": false
        },
        "total_time": {
          "name": "total_time",
          "type": "integer",
          "primaryKey": false,
          "notNull": false
        },
        "servings": {
          "name": "servings",
          "type": "integer",
          "primaryKey": false,
          "notNull": false
        },
        "source_url": {
          "name": "source_url",
          "type": "text",
          "primaryKey": false,
          "notNull": false
        },
        "created_at": {
          "name": "created_at",
          "type": "timestamp with time zone",
          "primaryKey": false,
          "notNull": true,
          "default": "now()"
        },
        "updated_at": {
          "name": "updated_at",
          "type": "timestamp with time zone",
          "primaryKey": false,
          "notNull": true,
          "default": "now()"
        }
      },
      "indexes": {
        "recipes_user_id_idx": {
          "name": "recipes_user_id_idx",
          "columns": [
            {
              "expression": "user_id",
              "isExpression": false,
              "asc": true,
              "nulls": "last"
            }
          ],
          "isUnique": false,
          "concurrently": false,
          "method": "btree",
          "with": {}
        }
      },
      "foreignKeys": {
        "recipes_user_id_users_id_fk": {
          "name": "recipes_user_id_users_id_fk",
          "tableFrom": "recipes",
          "tableTo": "users",
          "schemaTo": "auth",
          "columnsFrom": [
            "user_id"
          ],
          "columnsTo": [
            "id"
          ],
          "onDelete": "cascade",
          "onUpdate": "no action"
        }
      },
      "compositePrimaryKeys": {},
      "uniqueConstraints": {},
      "policies": {
        "recipes_select_own": {
          "name": "recipes_select_own",
          "as": "PERMISSIVE",
          "for": "SELECT",
          "to": [
            "authenticated"
          ],
          "using": "(select auth.uid()) is not null and (select auth.uid()) = \"recipes\".\"user_id\""
        },
        "recipes_insert_own": {
          "name": "recipes_insert_own",
          "as": "PERMISSIVE",
          "for": "INSERT",
          "to": [
            "authenticated"
          ],
          "withCheck": "(select auth.uid()) is not null and (select auth.uid()) = \"recipes\".\"user_id\""
        },
        "recipes_update_own": {
          "name": "recipes_update_own",
          "as": "PERMISSIVE",
          "for": "UPDATE",
          "to": [
            "authenticated"
          ],
          "using": "(select auth.uid()) is not null and (select auth.uid()) = \"recipes\".\"user_id\"",
          "withCheck": "(select auth.uid()) is not null and (select auth.uid()) = \"recipes\".\"user_id\""
        },
        "recipes_delete_own": {
          "name": "recipes_delete_own",
          "as": "PERMISSIVE",
          "for": "DELETE",
          "to": [
            "authenticated"
          ],
          "using": "(select auth.uid()) is not null and (select auth.uid()) = \"recipes\".\"user_id\""
        }
      },
      "checkConstraints": {},
      "isRLSEnabled": true
    }
  },
  "enums": {},
  "schemas": {},
  "sequences": {},
  "roles": {},
  "policies": {},
  "views": {},
  "_meta": {
    "columns": {},
    "schemas": {},
    "tables": {}
  }
}
